setup.py
ThreadDownloader1998.egg-info/PKG-INFO
ThreadDownloader1998.egg-info/SOURCES.txt
ThreadDownloader1998.egg-info/dependency_links.txt
ThreadDownloader1998.egg-info/top_level.txt
simpleThreading/Setup.py
simpleThreading/ThreadPool.py
simpleThreading/ThreadingFunction.py
simpleThreading/__init__.py