Metadata-Version: 1.0
Name: ThreadDownloader1998
Version: 1.0.0
Summary: My first pytyhon doistribution
Home-page: UNKNOWN
Author: UNKNOWN
Author-email: UNKNOWN
License: UNKNOWN
Platform: UNKNOWN
